{
  "version": "1.0.0",
  "lastScanned": 1775375538018,
  "projectRoot": "/Users/daffa/daffa/solid_template",
  "techStack": {
    "languages": [
      {
        "name": "JavaScript/TypeScript",
        "version": ">=22",
        "confidence": "high",
        "markers": [
          "package.json"
        ]
      },
      {
        "name": "TypeScript",
        "version": null,
        "confidence": "high",
        "markers": [
          "tsconfig.json"
        ]
      }
    ],
    "frameworks": [
      {
        "name": "solid-js",
        "version": "1.9.5",
        "category": "frontend"
      },
      {
        "name": "vite",
        "version": "7.0.0",
        "category": "build"
      }
    ],
    "packageManager": "pnpm",
    "runtime": "Node.js 22"
  },
  "build": {
    "buildCommand": "pnpm build",
    "testCommand": null,
    "lintCommand": null,
    "devCommand": "pnpm dev",
    "scripts": {
      "dev": "vite dev",
      "build": "vite build",
      "start": "vite start",
      "preview": "vite preview"
    }
  },
  "conventions": {
    "namingStyle": null,
    "importStyle": null,
    "testPattern": null,
    "fileOrganization": "type-based"
  },
  "structure": {
    "isMonorepo": false,
    "workspaces": [],
    "mainDirectories": [
      "public",
      "src"
    ],
    "gitBranches": null
  },
  "customNotes": [],
  "directoryMap": {
    "public": {
      "path": "public",
      "purpose": "Public files",
      "fileCount": 1,
      "lastAccessed": 1775375537977,
      "keyFiles": [
        "favicon.ico"
      ]
    },
    "src": {
      "path": "src",
      "purpose": "Source code",
      "fileCount": 5,
      "lastAccessed": 1775375537977,
      "keyFiles": [
        "app.css",
        "app.tsx",
        "entry-client.tsx",
        "entry-server.tsx",
        "global.d.ts"
      ]
    },
    "src/components": {
      "path": "src/components",
      "purpose": "UI components",
      "fileCount": 2,
      "lastAccessed": 1775375537978,
      "keyFiles": [
        "Counter.tsx",
        "Nav.tsx"
      ]
    },
    "src/lib": {
      "path": "src/lib",
      "purpose": "Library code",
      "fileCount": 2,
      "lastAccessed": 1775375537978,
      "keyFiles": [
        "createStorageSignal.ts",
        "storage.ts"
      ]
    },
    "src/routes": {
      "path": "src/routes",
      "purpose": "Route handlers",
      "fileCount": 3,
      "lastAccessed": 1775375537978,
      "keyFiles": [
        "[...404].tsx",
        "about.tsx",
        "index.tsx"
      ]
    }
  },
  "hotPaths": [
    {
      "path": "",
      "accessCount": 17,
      "lastAccessed": 1775446934441,
      "type": "directory"
    },
    {
      "path": "vite.config.ts",
      "accessCount": 13,
      "lastAccessed": 1775445459275,
      "type": "file"
    },
    {
      "path": "src/routes/index.tsx",
      "accessCount": 13,
      "lastAccessed": 1775449181643,
      "type": "file"
    },
    {
      "path": "src/components/Nav.tsx",
      "accessCount": 11,
      "lastAccessed": 1775448976857,
      "type": "file"
    },
    {
      "path": "src/routes/crops/[id].tsx",
      "accessCount": 11,
      "lastAccessed": 1775449317257,
      "type": "file"
    },
    {
      "path": "src/app.css",
      "accessCount": 10,
      "lastAccessed": 1775448789355,
      "type": "file"
    },
    {
      "path": "src/components/ThemeToggle.tsx",
      "accessCount": 10,
      "lastAccessed": 1775449009417,
      "type": "file"
    },
    {
      "path": "src/routes/guides/index.tsx",
      "accessCount": 9,
      "lastAccessed": 1775449366168,
      "type": "file"
    },
    {
      "path": "src",
      "accessCount": 9,
      "lastAccessed": 1775449399379,
      "type": "directory"
    },
    {
      "path": "src/routes/guides/[id].tsx",
      "accessCount": 8,
      "lastAccessed": 1775449299717,
      "type": "file"
    },
    {
      "path": "src/routes/characters/[id].tsx",
      "accessCount": 8,
      "lastAccessed": 1775449343436,
      "type": "file"
    },
    {
      "path": "package.json",
      "accessCount": 7,
      "lastAccessed": 1775445890284,
      "type": "file"
    },
    {
      "path": "src/components/LanguageToggle.tsx",
      "accessCount": 7,
      "lastAccessed": 1775448859400,
      "type": "file"
    },
    {
      "path": "src/components/DataCard.tsx",
      "accessCount": 7,
      "lastAccessed": 1775448924580,
      "type": "file"
    },
    {
      "path": "src/components/CategoryCard.tsx",
      "accessCount": 7,
      "lastAccessed": 1775448932937,
      "type": "file"
    },
    {
      "path": "src/components/Layout.tsx",
      "accessCount": 7,
      "lastAccessed": 1775448993367,
      "type": "file"
    },
    {
      "path": "src/components/Badge.tsx",
      "accessCount": 6,
      "lastAccessed": 1775448935674,
      "type": "file"
    },
    {
      "path": "src/components/FilterTabs.tsx",
      "accessCount": 6,
      "lastAccessed": 1775448965708,
      "type": "file"
    },
    {
      "path": "src/components/BookmarkButton.tsx",
      "accessCount": 6,
      "lastAccessed": 1775448992204,
      "type": "file"
    },
    {
      "path": "src/routes/events/[id].tsx",
      "accessCount": 6,
      "lastAccessed": 1775449279824,
      "type": "file"
    },
    {
      "path": "src/routes/festivals/[id].tsx",
      "accessCount": 6,
      "lastAccessed": 1775449318266,
      "type": "file"
    },
    {
      "path": "src/routes/bookmarks.tsx",
      "accessCount": 6,
      "lastAccessed": 1775449342041,
      "type": "file"
    },
    {
      "path": "src/components/SearchBar.tsx",
      "accessCount": 5,
      "lastAccessed": 1775448966589,
      "type": "file"
    },
    {
      "path": "wrangler.json",
      "accessCount": 4,
      "lastAccessed": 1775444779639,
      "type": "file"
    },
    {
      "path": "src/app.tsx",
      "accessCount": 4,
      "lastAccessed": 1775446910597,
      "type": "file"
    },
    {
      "path": "src/routes/about.tsx",
      "accessCount": 4,
      "lastAccessed": 1775448397671,
      "type": "file"
    },
    {
      "path": "src/routes/[...404].tsx",
      "accessCount": 4,
      "lastAccessed": 1775448581548,
      "type": "file"
    },
    {
      "path": "src/routes/characters/index.tsx",
      "accessCount": 4,
      "lastAccessed": 1775448754129,
      "type": "file"
    },
    {
      "path": "src/routes/recipes/[id].tsx",
      "accessCount": 4,
      "lastAccessed": 1775449276367,
      "type": "file"
    },
    {
      "path": "src/lib/createStorageSignal.ts",
      "accessCount": 2,
      "lastAccessed": 1775376088539,
      "type": "file"
    },
    {
      "path": "src/lib/storage.ts",
      "accessCount": 2,
      "lastAccessed": 1775376088606,
      "type": "file"
    },
    {
      "path": "src/lib/theme.ts",
      "accessCount": 2,
      "lastAccessed": 1775446918557,
      "type": "file"
    },
    {
      "path": "src/lib/i18n.ts",
      "accessCount": 2,
      "lastAccessed": 1775446918944,
      "type": "file"
    },
    {
      "path": "src/data/characters/types.ts",
      "accessCount": 2,
      "lastAccessed": 1775446925592,
      "type": "file"
    },
    {
      "path": "src/data/events/types.ts",
      "accessCount": 2,
      "lastAccessed": 1775448619008,
      "type": "file"
    },
    {
      "path": "src/data/festivals/types.ts",
      "accessCount": 2,
      "lastAccessed": 1775448619532,
      "type": "file"
    },
    {
      "path": "src/routes/festivals/index.tsx",
      "accessCount": 2,
      "lastAccessed": 1775448689913,
      "type": "file"
    },
    {
      "path": "src/routes/events/index.tsx",
      "accessCount": 2,
      "lastAccessed": 1775448735186,
      "type": "file"
    },
    {
      "path": "src/routes/crops/index.tsx",
      "accessCount": 2,
      "lastAccessed": 1775448857274,
      "type": "file"
    },
    {
      "path": "src/routes/recipes/index.tsx",
      "accessCount": 2,
      "lastAccessed": 1775448894928,
      "type": "file"
    },
    {
      "path": "src/routes/lists/index.tsx",
      "accessCount": 2,
      "lastAccessed": 1775448933311,
      "type": "file"
    },
    {
      "path": "tsconfig.json",
      "accessCount": 1,
      "lastAccessed": 1775375623806,
      "type": "file"
    },
    {
      "path": "src/components/Counter.tsx",
      "accessCount": 1,
      "lastAccessed": 1775375640219,
      "type": "file"
    },
    {
      "path": "src/data/items.ts",
      "accessCount": 1,
      "lastAccessed": 1775376107109,
      "type": "file"
    },
    {
      "path": "src/data",
      "accessCount": 1,
      "lastAccessed": 1775378544786,
      "type": "directory"
    },
    {
      "path": "src/data/recipes/types.ts",
      "accessCount": 1,
      "lastAccessed": 1775446339638,
      "type": "file"
    },
    {
      "path": "src/data/events/index.ts",
      "accessCount": 1,
      "lastAccessed": 1775446914269,
      "type": "file"
    },
    {
      "path": "src/data/festivals/index.ts",
      "accessCount": 1,
      "lastAccessed": 1775446914498,
      "type": "file"
    },
    {
      "path": "src/data/characters/index.ts",
      "accessCount": 1,
      "lastAccessed": 1775446926252,
      "type": "file"
    },
    {
      "path": "src/data/characters/rick.ts",
      "accessCount": 1,
      "lastAccessed": 1775446931022,
      "type": "file"
    }
  ],
  "userDirectives": []
}